{
  "manifest_schemas": [
    {
      "display_name": "Cell Line",
      "schema_name": "CellLine",
      "type": "record"
    },
    {
      "display_name": "Donor",
      "schema_name": "Donor",
      "type": "record"
    },
    {
      "display_name": "Resource",
      "schema_name": "Resource",
      "type": "record"
    },
    {
      "display_name": "Genetic Reagent",
      "schema_name": "GeneticReagent",
      "type": "record"
    },
    {
      "display_name": "Antibody",
      "schema_name": "Antibody",
      "type": "record"
    },
    {
      "display_name": "Animal Model",
      "schema_name": "AnimalModel",
      "type": "record"
    },
    {
      "display_name": "Usage",
      "schema_name": "Usage",
      "type": "record"
    },
    {
      "display_name": "Publication",
      "schema_name": "Publication",
      "type": "record"
    },
    {
      "display_name": "Biobank",
      "schema_name": "Biobank",
      "type": "record"
    },
    {
      "display_name": "Vendor Item",
      "schema_name": "VendorItem",
      "type": "record"
    },
    {
      "display_name": "Vendor",
      "schema_name": "Vendor",
      "type": "record"
    },
    {
      "display_name": "Observation",
      "schema_name": "Observation",
      "type": "record"
    },
    {
      "display_name": "Investigator",
      "schema_name": "Investigator",
      "type": "record"
    },
    {
      "display_name": "Resource Application",
      "schema_name": "ResourceApplication",
      "type": "record"
    },
    {
      "display_name": "Mutation",
      "schema_name": "Mutation",
      "type": "record"
    },
    {
      "display_name": "Mutation Details",
      "schema_name": "MutationDetails",
      "type": "record"
    },
    {
      "display_name": "Development",
      "schema_name": "Development",
      "type": "record"
    },
    {
      "display_name": "Funder",
      "schema_name": "Funder",
      "type": "record"
    }
  ],
  "service_version": "v23.6.1",
  "schema_version": ""
}